setup.py
wantao.py
wantao/__init__.py
wantao/wantao.py
wantao.egg-info/PKG-INFO
wantao.egg-info/SOURCES.txt
wantao.egg-info/dependency_links.txt
wantao.egg-info/not-zip-safe
wantao.egg-info/requires.txt
wantao.egg-info/top_level.txt