Metadata-Version: 1.0
Name: wantao
Version: 0.0.4
Summary: just a simple test
Home-page: https://github.com/wantao666/wantao
Author: wantao
Author-email: 895484122@qq.com
License: MIT License
Platform: UNKNOWN
